examples/__init__.py
examples/lol/__init__.py
examples/lol/lol_pipeline_transformer_example.py
examples/lol/data/__init__.py
examples/lol/data/subsample_lol_data.parquet
examples/lol/data/utils.py
examples/nba/__init__.py
examples/nba/nba_game_winner.py
examples/nba/nba_player_points_cv_example.py
examples/nba/data/__init__.py
examples/nba/data/game_player_subsample.parquet
examples/nba/data/utils.py
player_performance_ratings/__init__.py
player_performance_ratings/data_structures.py
player_performance_ratings/pipeline.py
player_performance_ratings/pipeline_factory.py
player_performance_ratings/pipeline_transformer.py
player_performance_ratings/transformation_pipeline.py
player_performance_ratings/utils.py
player_performance_ratings/cross_validator/__init__.py
player_performance_ratings/cross_validator/_base.py
player_performance_ratings/cross_validator/cross_validator.py
player_performance_ratings/predictor/__init__.py
player_performance_ratings/predictor/_base.py
player_performance_ratings/predictor/predictor.py
player_performance_ratings/predictor/sklearn_estimator.py
player_performance_ratings/predictor_transformer/__init__.py
player_performance_ratings/predictor_transformer/_simple_transformer.py
player_performance_ratings/predictor_transformer/transformer.py
player_performance_ratings/ratings/__init__.py
player_performance_ratings/ratings/enums.py
player_performance_ratings/ratings/league_identifier.py
player_performance_ratings/ratings/match_generator.py
player_performance_ratings/ratings/rating_generator.py
player_performance_ratings/ratings/update_rating_generator.py
player_performance_ratings/ratings/performance_generator/__init__.py
player_performance_ratings/ratings/performance_generator/performances_generator.py
player_performance_ratings/ratings/rating_calculators/__init__.py
player_performance_ratings/ratings/rating_calculators/match_rating_generator.py
player_performance_ratings/ratings/rating_calculators/performance_predictor.py
player_performance_ratings-5.27.0.dist-info/LICENSE
player_performance_ratings-5.27.0.dist-info/METADATA
player_performance_ratings-5.27.0.dist-info/WHEEL
player_performance_ratings-5.27.0.dist-info/top_level.txt
player_performance_ratings-5.27.0.dist-info/RECORD
