Metadata-Version: 2.2
Name: player-performance-ratings
Version: 5.27.0
Summary: Match Predictions based on Player Ratings
Home-page: https://github.com/Hiderdk/player-performance-ratings
Author: Mathias Holmstrøm
Author-email: mathiasholmstom@gmail.com
License-File: LICENSE
Requires-Dist: numpy>=1.23.4
Requires-Dist: optuna>=3.4.0
Requires-Dist: pandas>=2.0.0
Requires-Dist: pendulum>=1.0.0
Requires-Dist: scikit_learn>=1.3.1
Requires-Dist: lightgbm>=4.0.0
Requires-Dist: narwhals>=1.19.0
Requires-Dist: polars>=1.17.0
Requires-Dist: pyarrow
Requires-Dist: pyarrow>=19.0.0
Dynamic: author
Dynamic: author-email
Dynamic: description
Dynamic: description-content-type
Dynamic: home-page
Dynamic: requires-dist
Dynamic: summary
